[{"estudiante":"Peter","documento":1010,"correo":"peter@outlook.com","telefono":7100100,"cursoactual":2},{"estudiante":"Elkin","documento":1020,"correo":"ecordoba@outlook.com","telefono":7100101,"cursoactual":1},{"estudiante":"Jaime","documento":4564567,"correo":"jaime@gmail.com","telefono":4567856,"cursoactual":"4"},{"estudiante":"alex","documento":4564567,"correo":"as@gmail.com","telefono":4695598,"cursoactual":"6"},{"estudiante":"Jordi","documento":4564567,"correo":"jespitia@gmail.com","telefono":5630000,"cursoactual":"1"}]